wrapcco/__init__.py
wrapcco/core/__init__.py
wrapcco/core/_template.py
wrapcco/core/wrapper.py
wrapcco/resources/FunctionWrapper.hpp
wrapcco/resources/FunctionWrapper.py
wrapcco/resources/__init__.py
wrapcco/resources/cmd_setup.py
wrapcco/tools/__init__.py
wrapcco/tools/extension.py
wrapcco-0.1.3.dist-info/LICENSE
wrapcco-0.1.3.dist-info/METADATA
wrapcco-0.1.3.dist-info/WHEEL
wrapcco-0.1.3.dist-info/entry_points.txt
wrapcco-0.1.3.dist-info/top_level.txt
wrapcco-0.1.3.dist-info/RECORD
